[
  {
    "id": "SCV",
    "type": "worker",
    "target_value": 1,
    "priority": 290
  },
  {
    "id": "SCV",
    "type": "worker",
    "target_value": 1,
    "priority": 285
  },
  {
    "id": "SupplyDepot",
    "type": "structure",
    "target_value": 1,
    "priority": 280
  },
  {
    "id": "SCV",
    "type": "worker",
    "target_value": 1,
    "priority": 275
  },
  {
    "id": "Refinery",
    "type": "structure",
    "target_value": 1,
    "priority": 270
  },
  {
    "id": "Refinery",
    "type": "structure",
    "target_value": 1,
    "priority": 265
  },
  {
    "id": "worker_to_scout",
    "type": "action",
    "target_value": 1,
    "priority": 260
  },
  {
    "id": "SCV",
    "type": "worker",
    "target_value": 1,
    "priority": 255
  },
  {
    "id": "3worker_to_gas",
    "type": "action",
    "target_value": 1,
    "priority": 250
  },
  {
    "id": "SCV",
    "type": "worker",
    "target_value": 1,
    "priority": 245
  },
  {
    "id": "3worker_to_gas",
    "type": "action",
    "target_value": 1,
    "priority": 240
  },
  {
    "id": "SCV",
    "type": "worker",
    "target_value": 1,
    "priority": 235
  },
  {
    "id": "Barracks",
    "type": "structure",
    "target_value": 1,
    "priority": 230
  },
  {
    "id": "Barracks",
    "type": "structure",
    "target_value": 1,
    "priority": 225
  },
  {
    "id": "SCV",
    "type": "worker",
    "target_value": 1,
    "priority": 220
  },
  {
    "id": "SCV",
    "type": "worker",
    "target_value": 1,
    "priority": 215
  },
  {
    "id": "SCV",
    "type": "worker",
    "target_value": 1,
    "priority": 210
  },
  {
    "id": "Reaper",
    "type": "unit",
    "target_value": 1,
    "priority": 205
  },
  {
    "id": "OrbitalCommand",
    "type": "structure",
    "target_value": 1,
    "priority": 200
  },
  {
    "id": "SupplyDepot",
    "type": "structure",
    "target_value": 1,
    "priority": 195
  },
  {
    "id": "Reaper",
    "type": "unit",
    "target_value": 1,
    "priority": 190
  },
  {
    "id": "Factory",
    "type": "structure",
    "target_value": 1,
    "priority": 185
  },
  {
    "id": "call_down_mule",
    "type": "action",
    "target_value": 1,
    "priority": 180
  },
  {
    "id": "Barracks",
    "type": "structure",
    "target_value": 1,
    "priority": 175
  },
  {
    "id": "Reaper",
    "type": "unit",
    "target_value": 1,
    "priority": 170
  },
  {
    "id": "SCV",
    "type": "worker",
    "target_value": 1,
    "priority": 165
  },
  {
    "id": "SCV",
    "type": "worker",
    "target_value": 1,
    "priority": 160
  },
  {
    "id": "BarracksTechLab",
    "type": "structure",
    "target_value": 1,
    "priority": 155
  },
  {
    "id": "BarracksTechLab",
    "type": "structure",
    "target_value": 1,
    "priority": 150
  },
  {
    "id": "SupplyDepot",
    "type": "structure",
    "target_value": 1,
    "priority": 145
  },
  {
    "id": "FactoryTechLab",
    "type": "structure",
    "target_value": 1,
    "priority": 140
  },
  {
    "id": "Marine",
    "type": "unit",
    "target_value": 1,
    "priority": 135
  },
  {
    "id": "Stimpack",
    "type": "upgrade",
    "target_value": 1,
    "priority": 130
  },
  {
    "id": "SiegeTank",
    "type": "unit",
    "target_value": 1,
    "priority": 125
  },
  {
    "id": "BarracksReactor",
    "type": "structure",
    "target_value": 1,
    "priority": 120
  },
  {
    "id": "ShieldWall",
    "type": "upgrade",
    "target_value": 1,
    "priority": 115
  },
  {
    "id": "Marine",
    "type": "unit",
    "target_value": 1,
    "priority": 110
  },
  {
    "id": "Marine",
    "type": "unit",
    "target_value": 1,
    "priority": 105
  },
  {
    "id": "SupplyDepot",
    "type": "structure",
    "target_value": 1,
    "priority": 100
  },
  {
    "id": "call_down_mule",
    "type": "action",
    "target_value": 1,
    "priority": 95
  },
  {
    "id": "Marine",
    "type": "unit",
    "target_value": 1,
    "priority": 90
  },
  {
    "id": "Marine",
    "type": "unit",
    "target_value": 1,
    "priority": 85
  },
  {
    "id": "SiegeTank",
    "type": "unit",
    "target_value": 1,
    "priority": 80
  },
  {
    "id": "Marine",
    "type": "unit",
    "target_value": 1,
    "priority": 75
  },
  {
    "id": "Marine",
    "type": "unit",
    "target_value": 1,
    "priority": 70
  },
  {
    "id": "Marine",
    "type": "unit",
    "target_value": 1,
    "priority": 65
  },
  {
    "id": "SupplyDepot",
    "type": "structure",
    "target_value": 1,
    "priority": 60
  },
  {
    "id": "Marauder",
    "type": "unit",
    "target_value": 1,
    "priority": 55
  },
  {
    "id": "Marauder",
    "type": "unit",
    "target_value": 1,
    "priority": 50
  },
  {
    "id": "Marine",
    "type": "unit",
    "target_value": 1,
    "priority": 45
  },
  {
    "id": "Marine",
    "type": "unit",
    "target_value": 1,
    "priority": 40
  },
  {
    "id": "SiegeTank",
    "type": "unit",
    "target_value": 1,
    "priority": 35
  },
  {
    "id": "SupplyDepot",
    "type": "structure",
    "target_value": 1,
    "priority": 30
  },
  {
    "id": "call_down_mule",
    "type": "action",
    "target_value": 1,
    "priority": 25
  },
  {
    "id": "Marine",
    "type": "unit",
    "target_value": 1,
    "priority": 20
  },
  {
    "id": "Marine",
    "type": "unit",
    "target_value": 1,
    "priority": 15
  },
  {
    "id": "Marauder",
    "type": "unit",
    "target_value": 1,
    "priority": 10
  },
  {
    "id": "Marauder",
    "type": "unit",
    "target_value": 1,
    "priority": 5
  },
  {
    "id": "PunisherGrenades",
    "type": "upgrade",
    "target_value": 1,
    "priority": 0
  }
]