[
  {
    "id": "SCV",
    "type": "UNIT",
    "can_skip": true,
    "priority": 295,
    "target_value": 1,
    "comment": "Write comment here"
  },
  {
    "id": "SCV",
    "type": "UNIT",
    "can_skip": true,
    "priority": 290,
    "target_value": 1,
    "comment": "Write comment here"
  },
  {
    "id": "SUPPLYDEPOT",
    "type": "STRUCTURE",
    "can_skip": false,
    "priority": 285,
    "target_value": 1,
    "comment": "Write comment here"
  },
  {
    "id": "SCV",
    "type": "UNIT",
    "can_skip": true,
    "priority": 280,
    "target_value": 1,
    "comment": "Write comment here"
  },
  {
    "id": "REFINERY",
    "type": "STRUCTURE",
    "can_skip": false,
    "priority": 275,
    "target_value": 1,
    "comment": "Write comment here"
  },
  {
    "id": "REFINERY",
    "type": "STRUCTURE",
    "can_skip": false,
    "priority": 270,
    "target_value": 1,
    "comment": "Write comment here"
  },
  {
    "id": "WORKER_TO_SCOUT",
    "type": "ACTION",
    "can_skip": true,
    "priority": 265,
    "target_value": 1,
    "comment": "Write comment here"
  },
  {
    "id": "SCV",
    "type": "UNIT",
    "can_skip": true,
    "priority": 260,
    "target_value": 1,
    "comment": "Write comment here"
  },
  {
    "id": "3WORKER_TO_GAS",
    "type": "ACTION",
    "can_skip": true,
    "priority": 255,
    "target_value": 1,
    "comment": "Write comment here"
  },
  {
    "id": "SCV",
    "type": "UNIT",
    "can_skip": true,
    "priority": 250,
    "target_value": 1,
    "comment": "Write comment here"
  },
  {
    "id": "3WORKER_TO_GAS",
    "type": "ACTION",
    "can_skip": true,
    "priority": 245,
    "target_value": 1,
    "comment": "Write comment here"
  },
  {
    "id": "SCV",
    "type": "UNIT",
    "can_skip": true,
    "priority": 240,
    "target_value": 1,
    "comment": "Write comment here"
  },
  {
    "id": "BARRACKS",
    "type": "STRUCTURE",
    "can_skip": false,
    "priority": 235,
    "target_value": 1,
    "comment": "Write comment here"
  },
  {
    "id": "BARRACKS",
    "type": "STRUCTURE",
    "can_skip": false,
    "priority": 230,
    "target_value": 1,
    "comment": "Write comment here"
  },
  {
    "id": "SCV",
    "type": "UNIT",
    "can_skip": true,
    "priority": 225,
    "target_value": 1,
    "comment": "Write comment here"
  },
  {
    "id": "SCV",
    "type": "UNIT",
    "can_skip": true,
    "priority": 220,
    "target_value": 1,
    "comment": "Write comment here"
  },
  {
    "id": "SCV",
    "type": "UNIT",
    "can_skip": true,
    "priority": 215,
    "target_value": 1,
    "comment": "Write comment here"
  },
  {
    "id": "REAPER",
    "type": "UNIT",
    "can_skip": true,
    "priority": 210,
    "target_value": 1,
    "comment": "Write comment here"
  },
  {
    "id": "ORBITALCOMMAND",
    "type": "TECH",
    "can_skip": true,
    "priority": 205,
    "target_value": 1,
    "comment": "Write comment here"
  },
  {
    "id": "SUPPLYDEPOT",
    "type": "STRUCTURE",
    "can_skip": false,
    "priority": 200,
    "target_value": 1,
    "comment": "Write comment here"
  },
  {
    "id": "REAPER",
    "type": "UNIT",
    "can_skip": true,
    "priority": 195,
    "target_value": 1,
    "comment": "Write comment here"
  },
  {
    "id": "FACTORY",
    "type": "STRUCTURE",
    "can_skip": false,
    "priority": 190,
    "target_value": 1,
    "comment": "Write comment here"
  },
  {
    "id": "CALL_DOWN_MULE",
    "type": "ACTION",
    "can_skip": true,
    "priority": 185,
    "target_value": 1,
    "comment": "Write comment here"
  },
  {
    "id": "BARRACKS",
    "type": "STRUCTURE",
    "can_skip": false,
    "priority": 180,
    "target_value": 1,
    "comment": "Write comment here"
  },
  {
    "id": "REAPER",
    "type": "UNIT",
    "can_skip": true,
    "priority": 175,
    "target_value": 1,
    "comment": "Write comment here"
  },
  {
    "id": "SCV",
    "type": "UNIT",
    "can_skip": true,
    "priority": 170,
    "target_value": 1,
    "comment": "Write comment here"
  },
  {
    "id": "SCV",
    "type": "UNIT",
    "can_skip": true,
    "priority": 165,
    "target_value": 1,
    "comment": "Write comment here"
  },
  {
    "id": "BARRACKSTECHLAB",
    "type": "TECH",
    "can_skip": true,
    "priority": 160,
    "target_value": 1,
    "comment": "Write comment here"
  },
  {
    "id": "BARRACKSTECHLAB",
    "type": "TECH",
    "can_skip": true,
    "priority": 155,
    "target_value": 1,
    "comment": "Write comment here"
  },
  {
    "id": "SUPPLYDEPOT",
    "type": "STRUCTURE",
    "can_skip": false,
    "priority": 150,
    "target_value": 1,
    "comment": "Write comment here"
  },
  {
    "id": "FACTORYTECHLAB",
    "type": "TECH",
    "can_skip": true,
    "priority": 145,
    "target_value": 1,
    "comment": "Write comment here"
  },
  {
    "id": "MARINE",
    "type": "UNIT",
    "can_skip": true,
    "priority": 140,
    "target_value": 1,
    "comment": "Write comment here"
  },
  {
    "id": "STIMPACK",
    "type": "TECH",
    "can_skip": true,
    "priority": 135,
    "target_value": 1,
    "comment": "Write comment here"
  },
  {
    "id": "SIEGETANK",
    "type": "UNIT",
    "can_skip": true,
    "priority": 130,
    "target_value": 1,
    "comment": "Write comment here"
  },
  {
    "id": "BARRACKSREACTOR",
    "type": "TECH",
    "can_skip": true,
    "priority": 125,
    "target_value": 1,
    "comment": "Write comment here"
  },
  {
    "id": "SHIELDWALL",
    "type": "TECH",
    "can_skip": true,
    "priority": 120,
    "target_value": 1,
    "comment": "Write comment here"
  },
  {
    "id": "MARINE",
    "type": "UNIT",
    "can_skip": true,
    "priority": 115,
    "target_value": 1,
    "comment": "Write comment here"
  },
  {
    "id": "MARINE",
    "type": "UNIT",
    "can_skip": true,
    "priority": 110,
    "target_value": 1,
    "comment": "Write comment here"
  },
  {
    "id": "SUPPLYDEPOT",
    "type": "STRUCTURE",
    "can_skip": false,
    "priority": 105,
    "target_value": 1,
    "comment": "Write comment here"
  },
  {
    "id": "CALL_DOWN_MULE",
    "type": "ACTION",
    "can_skip": true,
    "priority": 100,
    "target_value": 1,
    "comment": "Write comment here"
  },
  {
    "id": "MARINE",
    "type": "UNIT",
    "can_skip": true,
    "priority": 95,
    "target_value": 1,
    "comment": "Write comment here"
  },
  {
    "id": "MARINE",
    "type": "UNIT",
    "can_skip": true,
    "priority": 90,
    "target_value": 1,
    "comment": "Write comment here"
  },
  {
    "id": "SIEGETANK",
    "type": "UNIT",
    "can_skip": true,
    "priority": 85,
    "target_value": 1,
    "comment": "Write comment here"
  },
  {
    "id": "MARINE",
    "type": "UNIT",
    "can_skip": true,
    "priority": 80,
    "target_value": 1,
    "comment": "Write comment here"
  },
  {
    "id": "MARINE",
    "type": "UNIT",
    "can_skip": true,
    "priority": 75,
    "target_value": 1,
    "comment": "Write comment here"
  },
  {
    "id": "MARINE",
    "type": "UNIT",
    "can_skip": true,
    "priority": 70,
    "target_value": 1,
    "comment": "Write comment here"
  },
  {
    "id": "SUPPLYDEPOT",
    "type": "STRUCTURE",
    "can_skip": false,
    "priority": 65,
    "target_value": 1,
    "comment": "Write comment here"
  },
  {
    "id": "MARAUDER",
    "type": "UNIT",
    "can_skip": true,
    "priority": 60,
    "target_value": 1,
    "comment": "Write comment here"
  },
  {
    "id": "MARAUDER",
    "type": "UNIT",
    "can_skip": true,
    "priority": 55,
    "target_value": 1,
    "comment": "Write comment here"
  },
  {
    "id": "MARINE",
    "type": "UNIT",
    "can_skip": true,
    "priority": 50,
    "target_value": 1,
    "comment": "Write comment here"
  },
  {
    "id": "MARINE",
    "type": "UNIT",
    "can_skip": true,
    "priority": 45,
    "target_value": 1,
    "comment": "Write comment here"
  },
  {
    "id": "SIEGETANK",
    "type": "UNIT",
    "can_skip": true,
    "priority": 40,
    "target_value": 1,
    "comment": "Write comment here"
  },
  {
    "id": "SUPPLYDEPOT",
    "type": "STRUCTURE",
    "can_skip": false,
    "priority": 35,
    "target_value": 1,
    "comment": "Write comment here"
  },
  {
    "id": "CALL_DOWN_MULE",
    "type": "ACTION",
    "can_skip": true,
    "priority": 30,
    "target_value": 1,
    "comment": "Write comment here"
  },
  {
    "id": "MARINE",
    "type": "UNIT",
    "can_skip": true,
    "priority": 25,
    "target_value": 1,
    "comment": "Write comment here"
  },
  {
    "id": "MARINE",
    "type": "UNIT",
    "can_skip": true,
    "priority": 20,
    "target_value": 1,
    "comment": "Write comment here"
  },
  {
    "id": "MARAUDER",
    "type": "UNIT",
    "can_skip": true,
    "priority": 15,
    "target_value": 1,
    "comment": "Write comment here"
  },
  {
    "id": "MARAUDER",
    "type": "UNIT",
    "can_skip": true,
    "priority": 10,
    "target_value": 1,
    "comment": "Write comment here"
  },
  {
    "id": "PUNISHERGRENADES",
    "type": "TECH",
    "can_skip": true,
    "priority": 5,
    "target_value": 1,
    "comment": "Write comment here"
  }
]